ngiriapi/__init__.py
ngiriapi/_compat.py
ngiriapi/_exception_handler.py
ngiriapi/_utils.py
ngiriapi/applications.py
ngiriapi/authentication.py
ngiriapi/background.py
ngiriapi/concurrency.py
ngiriapi/config.py
ngiriapi/convertors.py
ngiriapi/datastructures.py
ngiriapi/endpoints.py
ngiriapi/exceptions.py
ngiriapi/formparsers.py
ngiriapi/py.typed
ngiriapi/requests.py
ngiriapi/responses.py
ngiriapi/routing.py
ngiriapi/schemas.py
ngiriapi/staticfiles.py
ngiriapi/status.py
ngiriapi/templating.py
ngiriapi/testclient.py
ngiriapi/types.py
ngiriapi/websockets.py
ngiriapi/middleware/__init__.py
ngiriapi/middleware/authentication.py
ngiriapi/middleware/base.py
ngiriapi/middleware/cors.py
ngiriapi/middleware/errors.py
ngiriapi/middleware/exceptions.py
ngiriapi/middleware/gzip.py
ngiriapi/middleware/httpsredirect.py
ngiriapi/middleware/sessions.py
ngiriapi/middleware/trustedhost.py
ngiriapi/middleware/wsgi.py
ngiriapi-0.0.2.dist-info/METADATA
ngiriapi-0.0.2.dist-info/WHEEL
ngiriapi-0.0.2.dist-info/licenses/LICENSE
ngiriapi-0.0.2.dist-info/RECORD
