Metadata-Version: 2.1
Name: Ngiriapi
Version: 0.0.2
Summary: The Smalest ASGI library to power your api in python.
Project-URL: Homepage, https://github.com/pesaply/ngiriapi
Project-URL: Documentation, https://www.ngiri.co.tz/
Project-URL: Changelog, https://www.ngiri.co.tz/release-notes/
Project-URL: Funding, https://github.com/sponsors/pesaply
Project-URL: Source, https://github.com/pesaply/ngiriapi
Author-email: Mark Francis <ngiriapp@gmail.com>
License-Expression: BSD-3-Clause
License-File: LICENSE
Classifier: Development Status :: 3 - Alpha
Classifier: Environment :: Web Environment
Classifier: Framework :: AnyIO
Classifier: Intended Audience :: Developers
Classifier: License :: OSI Approved :: BSD License
Classifier: Operating System :: OS Independent
Classifier: Programming Language :: Python :: 3
Classifier: Programming Language :: Python :: 3.8
Classifier: Programming Language :: Python :: 3.9
Classifier: Programming Language :: Python :: 3.10
Classifier: Programming Language :: Python :: 3.11
Classifier: Programming Language :: Python :: 3.12
Classifier: Topic :: Internet :: WWW/HTTP
Requires-Python: >=3.8
Requires-Dist: anyio<5,>=3.4.0
Requires-Dist: typing-extensions>=3.10.0; python_version < '3.10'
Provides-Extra: full
Requires-Dist: itsdangerous; extra == 'full'
Requires-Dist: jinja2; extra == 'full'
Requires-Dist: ngiri>=0.0.3; extra == 'full'
Requires-Dist: python-multipart; extra == 'full'
Requires-Dist: pyyaml; extra == 'full'
